{
  "common-mistakes": {
    "id": "dr-gardner-mistakes",
    "category": "닥터가드너-문제해결",
    "title": "초보자가 자주 하는 실수들",
    "content": "세컨드브레인 OS를 처음 사용할 때 흔히 발생하는 실수와 해결 방법입니다.",
    "tags": ["실수", "초보자", "주의사항"],
    "mistakes": [
      {
        "mistake": "모든 것을 프로젝트로 만들기",
        "why": "프로젝트의 정의를 잘못 이해",
        "correct": "2개 이상 할일 + 종료일 있을 때만",
        "example": {
          "wrong": "책 읽기 (프로젝트)",
          "right": "책 읽기 (할일) → 독서 노트 작성 프로젝트"
        }
      },
      {
        "mistake": "수집할 때 분류하려고 하기",
        "why": "완벽주의적 성향",
        "correct": "일단 수집 → 나중에 명료화",
        "tip": "수집은 2초, 명료화는 20초"
      },
      {
        "mistake": "영역을 너무 세분화",
        "why": "주제별 분류 습관",
        "correct": "5-7개 큰 영역으로 충분",
        "example": {
          "wrong": "요리, 베이킹, 카페 (각각 영역)",
          "right": "취미 (영역) 안에 모두 포함"
        }
      },
      {
        "mistake": "노트를 너무 길게 작성",
        "why": "모든 내용을 한 곳에",
        "correct": "원자적 노트 - 한 노트 한 아이디어",
        "benefit": "재사용과 연결이 쉬워짐"
      },
      {
        "mistake": "아카이브를 쓰레기통으로 생각",
        "why": "완료=버리기로 오해",
        "correct": "과거의 자산 보관소",
        "use": "새 프로젝트 시작할 때 먼저 확인"
      }
    ]
  },

  "system-optimization": {
    "id": "dr-gardner-optimization",
    "category": "닥터가드너-문제해결",
    "title": "시스템 최적화 방법",
    "content": "세컨드브레인 OS가 느려지거나 복잡해졌을 때 최적화하는 방법입니다.",
    "tags": ["최적화", "성능", "정리"],
    "symptoms": [
      "페이지 로딩이 느림",
      "검색이 잘 안됨",
      "시스템이 복잡해 보임",
      "사용하기 부담스러움"
    ],
    "solutions": [
      {
        "issue": "데이터베이스 과부하",
        "signs": ["로딩 지연", "스크롤 버벅임"],
        "fixes": [
          "완료된 항목 아카이브로 이동",
          "오래된 노트 정리",
          "이미지 최적화 (압축)",
          "불필요한 관계 제거"
        ]
      },
      {
        "issue": "복잡한 구조",
        "signs": ["어디에 뭐가 있는지 모름", "너무 많은 뷰"],
        "fixes": [
          "핵심 페이지만 즐겨찾기",
          "사용 안하는 뷰 숨기기",
          "영역 통합 (5-7개 유지)",
          "단순한 워크플로우로 회귀"
        ]
      },
      {
        "issue": "검색 효율 저하",
        "signs": ["원하는 노트 못찾음", "검색 결과 너무 많음"],
        "fixes": [
          "제목에 키워드 포함",
          "태그 일관성 있게 사용",
          "정기적 노트 제목 리뷰",
          "중복 노트 병합"
        ]
      }
    ],
    "maintenance": {
      "daily": ["수집함 비우기", "완료 항목 체크"],
      "weekly": ["프로젝트 상태 업데이트", "노트 정리"],
      "monthly": ["아카이브 정리", "시스템 전체 리뷰"],
      "quarterly": ["영역/자원 재구성", "워크플로우 개선"]
    }
  },

  "specific-problems": {
    "id": "dr-gardner-specific",
    "category": "닥터가드너-문제해결",
    "title": "구체적 문제 상황별 해결법",
    "content": "사용자들이 자주 겪는 구체적인 문제 상황과 단계별 해결 방법입니다.",
    "tags": ["문제해결", "FAQ", "구체적상황"],
    "problems": [
      {
        "problem": "수집함이 100개 넘게 쌓였어요",
        "severity": "높음",
        "solution": [
          "당황하지 말고 일단 수집 중단",
          "2분 규칙 적용해서 빠른 것부터 처리",
          "오래된 것은 과감히 삭제 고려",
          "하루 30개씩 나눠서 처리",
          "앞으로는 매일 명료화 습관"
        ],
        "prevention": "매일 정해진 시간에 20분 명료화"
      },
      {
        "problem": "프로젝트와 할일 구분이 어려워요",
        "severity": "중간",
        "solution": [
          "단계가 2개 이상? → 프로젝트",
          "하루 안에 끝? → 할일",
          "불확실하면 일단 할일로 시작",
          "나중에 프로젝트로 승격 가능"
        ],
        "examples": [
          "이메일 보내기 → 할일",
          "제안서 작성 → 프로젝트 (조사+작성+검토)",
          "병원 예약 → 할일",
          "건강 검진 받기 → 프로젝트 (예약+검사+결과확인)"
        ]
      },
      {
        "problem": "노트를 어디에 넣을지 모르겠어요",
        "severity": "낮음",
        "solution": [
          "현재 프로젝트와 관련? → 프로젝트",
          "지속적 관심사? → 영역/자원",
          "둘 다 해당? → 둘 다 연결",
          "모르겠으면 일단 수집함에"
        ],
        "tip": "노션은 한 노트가 여러 곳에 있을 수 있음"
      },
      {
        "problem": "매일 하는 일을 어떻게 관리하나요",
        "severity": "중간",
        "solution": [
          "반복 할일은 프로젝트 템플릿으로",
          "버튼으로 자동 생성",
          "체크리스트 노트 활용",
          "습관 추적은 별도 데이터베이스"
        ],
        "example": "매일 운동 → 월간 운동 프로젝트 + 일일 체크"
      }
    ]
  },

  "migration-guide": {
    "id": "dr-gardner-migration",
    "category": "닥터가드너-문제해결",
    "title": "기존 시스템에서 마이그레이션",
    "content": "다른 노트 앱이나 이전 버전에서 세컨드브레인 OS로 옮기는 방법입니다.",
    "tags": ["마이그레이션", "데이터이전", "업그레이드"],
    "fromOtherApps": {
      "notion": {
        "from": "일반 노션 사용",
        "steps": [
          "기존 데이터베이스 CSV 내보내기",
          "세컨드브레인 OS 복제",
          "데이터 가져오기 (속성 매칭)",
          "관계 재설정",
          "단계적 전환 (병행 사용)"
        ]
      },
      "obsidian": {
        "from": "옵시디언",
        "steps": [
          "마크다운 파일 압축",
          "노션으로 가져오기",
          "PARA 구조로 재분류",
          "링크 관계 재구성"
        ]
      },
      "evernote": {
        "from": "에버노트/원노트",
        "steps": [
          "노트 내보내기 (HTML)",
          "노션 웹클리퍼로 가져오기",
          "노트 원자성 적용",
          "PARA 분류"
        ]
      }
    },
    "fromOldVersion": {
      "preparation": [
        "현재 템플릿 백업",
        "중요 데이터 목록 작성",
        "커스텀 설정 기록"
      ],
      "dataTransfer": [
        "할일: 전체 선택 → 이동",
        "노트: 카테고리 삭제 후 이동",
        "프로젝트: 상태 확인 후 이동",
        "관계: 수동 재연결 필요"
      ],
      "tips": [
        "한 번에 하지 말고 단계적으로",
        "핵심 데이터부터 이전",
        "일주일 정도 병행 사용",
        "문제 발생시 백업에서 복원"
      ]
    }
  },

  "performance-tips": {
    "id": "dr-gardner-performance",
    "category": "닥터가드너-문제해결",
    "title": "성능 향상 팁",
    "content": "세컨드브레인 OS를 빠르고 쾌적하게 사용하는 방법입니다.",
    "tags": ["성능", "속도", "최적화"],
    "generalTips": [
      {
        "tip": "갤러리뷰보다 테이블뷰 사용",
        "reason": "로딩 속도 향상"
      },
      {
        "tip": "필터 저장해서 재사용",
        "reason": "매번 설정 불필요"
      },
      {
        "tip": "큰 이미지는 외부 링크로",
        "reason": "페이지 용량 축소"
      },
      {
        "tip": "관계는 필요한 것만",
        "reason": "복잡도 감소"
      }
    ],
    "mobileOptimization": [
      "오프라인 사용 가능 설정",
      "이미지 자동 압축 활용",
      "심플한 모바일 전용 뷰",
      "자주 쓰는 페이지 캐싱"
    ],
    "shortcuts": [
      "Cmd/Ctrl + P: 빠른 검색",
      "Cmd/Ctrl + K: 링크 생성",
      "/: 블록 명령어",
      "[[: 페이지 연결"
    ]
  },

  "community-solutions": {
    "id": "dr-gardner-community",
    "category": "닥터가드너-문제해결",
    "title": "커뮤니티 솔루션 모음",
    "content": "사용자들이 발견한 창의적인 해결책과 활용법입니다.",
    "tags": ["커뮤니티", "팁", "활용법"],
    "creativeSolutions": [
      {
        "problem": "회의록 관리",
        "solution": "회의 프로젝트 + 참석자 태그 + 액션아이템 자동 추출",
        "sharedBy": "직장인 사용자"
      },
      {
        "problem": "독서 관리",
        "solution": "책별 프로젝트 + 원자적 인사이트 노트 + 독서 통계 대시보드",
        "sharedBy": "다독가 사용자"
      },
      {
        "problem": "루틴 관리",
        "solution": "요일별 템플릿 + 버튼 자동화 + 습관 체크리스트",
        "sharedBy": "자기계발 사용자"
      }
    ],
    "customWorkflows": [
      {
        "name": "주간 스프린트",
        "description": "1주일 단위 미니 프로젝트로 관리",
        "benefit": "단기 목표 달성률 향상"
      },
      {
        "name": "3-2-1 리뷰",
        "description": "3개 성과, 2개 배운점, 1개 개선점",
        "benefit": "간단하지만 효과적인 회고"
      }
    ],
    "resources": [
      "네이버 카페 질문 게시판",
      "유튜브 댓글 팁 모음",
      "사용자 제작 템플릿 공유"
    ]
  }
}